odoo8_addon_logistic_consignee-8.0.0.1.0-py2.7-nspkg.pth
odoo_addons/logistic_consignee/__openerp__.py
odoo_addons/logistic_consignee/__init__.py
odoo_addons/logistic_consignee/README.rst
odoo_addons/logistic_consignee/i18n/logistic_consignee.pot
odoo_addons/logistic_consignee/model/res_partner.py
odoo_addons/logistic_consignee/tests/test_consignee_sale_order.py
odoo_addons/logistic_consignee/tests/test_consignee_purchase_order.py
odoo_addons/logistic_consignee/tests/__init__.py
odoo8_addon_logistic_consignee-8.0.0.1.0.dist-info/top_level.txt
odoo8_addon_logistic_consignee-8.0.0.1.0.dist-info/WHEEL
odoo8_addon_logistic_consignee-8.0.0.1.0.dist-info/RECORD
odoo8_addon_logistic_consignee-8.0.0.1.0.dist-info/metadata.json
odoo8_addon_logistic_consignee-8.0.0.1.0.dist-info/DESCRIPTION.rst
odoo8_addon_logistic_consignee-8.0.0.1.0.dist-info/METADATA
odoo8_addon_logistic_consignee-8.0.0.1.0.dist-info/namespace_packages.txt
