Metadata-Version: 2.0
Name: odoo8-addon-logistic-consignee
Version: 8.0.0.1.0
Summary: Deprecated: use purchase_requisition_transport_multi_address, purchase_transport_multi_address, sale_transport_multi_address, stock_transport_multi_address
Home-page: http://www.camptocamp.com
Author: UNKNOWN
Author-email: UNKNOWN
License: AGPL-3
Platform: UNKNOWN
Requires-Dist: odoo (<9.0a,>=8.0a)
Requires-Dist: odoo8-addon-purchase-requisition-transport-multi-address
Requires-Dist: odoo8-addon-sale-transport-multi-address
Classifier: Programming Language :: Python :: 2.7
Classifier: Framework :: Odoo
Classifier: License :: OSI Approved :: GNU Affero General Public License v3
